[{"id":"A1B89B39-A746-4E55-9FAB-A128FF966426","element":"Label","text":"Label","static":true,"required":false,"bold":false,"italic":false,"content":"Placeholder text...","canHavePageBreakBefore":true,"canHaveAlternateForm":true,"canHaveDisplayHorizontal":true,"canHaveOptionCorrect":true,"canHaveOptionValue":true,"canPopulateFromApi":true},{"id":"12239C6F-9DFE-4CAB-A20B-7AF37D825AB2","element":"Dropdown","text":"Dropdown","required":false,"canHaveAnswer":true,"canHavePageBreakBefore":true,"canHaveAlternateForm":true,"canHaveDisplayHorizontal":true,"canHaveOptionCorrect":true,"canHaveOptionValue":true,"canPopulateFromApi":true,"field_name":"dropdown_B1BC35E1-BADF-4FA9-88BD-685BF06FD040","label":"Placeholder label","options":[{"value":"place_holder_option_1","text":"Place holder option 1","key":"dropdown_option_7B909A7F-5ED8-4DFA-93DB-2BFCBFC2B62F"},{"value":"place_holder_option_2","text":"Place holder option 2","key":"dropdown_option_ECF351B6-4337-4DEC-A286-5FA7739C6212"},{"value":"place_holder_option_3","text":"Place holder option 3","key":"dropdown_option_DFC9363E-54DA-4EA7-9A2B-3A263E20EEF6"}]}]